[{"no":1,"title":"a","content":"a","writer":"a","password":"a","viewCount":0,"createdDate":1660189663887},{"no":4,"title":"aaaa","content":"bbbb","writer":"acu","password":"1111","viewCount":0,"createdDate":1660707229387},{"no":5,"title":"no","content":"nono","writer":"nok","password":"1111","viewCount":0,"createdDate":1660708454573},{"no":7,"title":"hihi","content":"hihihihi","writer":"sik","password":"11","viewCount":0,"createdDate":1660810855776},{"no":9,"title":"lplplp","content":"lplplp","writer":"an","password":"1111","viewCount":11,"createdDate":1660878010879},{"no":10,"title":"xxxx","content":"xxxxx","writer":"an","password":"1111","viewCount":11,"createdDate":1660879014118},{"no":11,"title":"yaho","content":"yaho","writer":"an","password":"1111","viewCount":0,"createdDate":1660880212926}]